{"timestamp": "2024-11-02T08:38:01.995682", "state": {"master_account": {}, "test-dev": {"binance_perpetual_testnet": [{"token": "USDT", "units": 15000.0, "price": 1.0, "value": 15000.0, "available_units": 15000.0}]}, "mohit-test": {}}}
{"timestamp": "2024-11-02T08:38:01.998704", "state": {"master_account": {}, "test-dev": {"binance_perpetual_testnet": [{"token": "USDT", "units": 15000.0, "price": 1.0, "value": 15000.0, "available_units": 15000.0}]}, "mohit-test": {}}}
{"timestamp": "2024-11-02T08:38:02.003537", "state": {"master_account": {}, "test-dev": {"binance_perpetual_testnet": [{"token": "USDT", "units": 15000.0, "price": 1.0, "value": 15000.0, "available_units": 15000.0}]}, "mohit-test": {}}}
{"timestamp": "2024-11-02T08:39:00.001906", "state": {"master_account": {}, "test-dev": {"binance_perpetual_testnet": [{"token": "USDT", "units": 15000.0, "price": 1.0, "value": 15000.0, "available_units": 15000.0}]}, "mohit-test": {}}}
{"timestamp": "2024-11-02T08:39:00.003516", "state": {"master_account": {}, "test-dev": {"binance_perpetual_testnet": [{"token": "USDT", "units": 15000.0, "price": 1.0, "value": 15000.0, "available_units": 15000.0}]}, "mohit-test": {}}}
{"timestamp": "2024-11-02T08:40:00.000440", "state": {"master_account": {}, "test-dev": {"binance_perpetual_testnet": [{"token": "USDT", "units": 15000.0, "price": 1.0, "value": 15000.0, "available_units": 15000.0}]}, "mohit-test": {}}}
{"timestamp": "2024-11-02T08:40:00.000952", "state": {"master_account": {}, "test-dev": {"binance_perpetual_testnet": [{"token": "USDT", "units": 15000.0, "price": 1.0, "value": 15000.0, "available_units": 15000.0}]}, "mohit-test": {}}}
{"timestamp": "2024-11-02T08:41:00.001096", "state": {"master_account": {}, "test-dev": {"binance_perpetual_testnet": [{"token": "USDT", "units": 15000.0, "price": 1.0, "value": 15000.0, "available_units": 15000.0}]}, "mohit-test": {}}}
{"timestamp": "2024-11-02T08:41:00.001826", "state": {"master_account": {}, "test-dev": {"binance_perpetual_testnet": [{"token": "USDT", "units": 15000.0, "price": 1.0, "value": 15000.0, "available_units": 15000.0}]}, "mohit-test": {}}}
{"timestamp": "2024-11-02T08:42:00.000812", "state": {"master_account": {}, "test-dev": {"binance_perpetual_testnet": [{"token": "USDT", "units": 15000.0, "price": 1.0, "value": 15000.0, "available_units": 15000.0}]}, "mohit-test": {}}}
{"timestamp": "2024-11-02T08:42:00.002448", "state": {"master_account": {}, "test-dev": {"binance_perpetual_testnet": [{"token": "USDT", "units": 15000.0, "price": 1.0, "value": 15000.0, "available_units": 15000.0}]}, "mohit-test": {}}}
{"timestamp": "2024-11-02T08:42:59.999903", "state": {"master_account": {}, "test-dev": {"binance_perpetual_testnet": [{"token": "USDT", "units": 15000.0, "price": 1.0, "value": 15000.0, "available_units": 15000.0}]}, "mohit-test": {}}}
{"timestamp": "2024-11-02T08:43:00.000591", "state": {"master_account": {}, "test-dev": {"binance_perpetual_testnet": [{"token": "USDT", "units": 15000.0, "price": 1.0, "value": 15000.0, "available_units": 15000.0}]}, "mohit-test": {}}}
{"timestamp": "2024-11-02T08:44:00.003983", "state": {"master_account": {}, "test-dev": {"binance_perpetual_testnet": [{"token": "USDT", "units": 15000.0, "price": 1.0, "value": 15000.0, "available_units": 15000.0}]}, "mohit-test": {}}}
{"timestamp": "2024-11-02T08:44:00.009047", "state": {"master_account": {}, "test-dev": {"binance_perpetual_testnet": [{"token": "USDT", "units": 15000.0, "price": 1.0, "value": 15000.0, "available_units": 15000.0}]}, "mohit-test": {}}}
{"timestamp": "2024-11-02T08:45:00.001036", "state": {"master_account": {}, "test-dev": {"binance_perpetual_testnet": [{"token": "USDT", "units": 15000.0, "price": 1.0, "value": 15000.0, "available_units": 15000.0}]}, "mohit-test": {}}}
{"timestamp": "2024-11-02T08:45:00.001508", "state": {"master_account": {}, "test-dev": {"binance_perpetual_testnet": [{"token": "USDT", "units": 15000.0, "price": 1.0, "value": 15000.0, "available_units": 15000.0}]}, "mohit-test": {}}}
{"timestamp": "2024-11-02T08:46:00.000108", "state": {"master_account": {}, "test-dev": {"binance_perpetual_testnet": [{"token": "USDT", "units": 15000.0, "price": 1.0, "value": 15000.0, "available_units": 15000.0}]}, "mohit-test": {}}}
{"timestamp": "2024-11-02T08:46:00.001278", "state": {"master_account": {}, "test-dev": {"binance_perpetual_testnet": [{"token": "USDT", "units": 15000.0, "price": 1.0, "value": 15000.0, "available_units": 15000.0}]}, "mohit-test": {}}}
{"timestamp": "2024-11-02T08:47:00.000489", "state": {"master_account": {}, "test-dev": {"binance_perpetual_testnet": [{"token": "USDT", "units": 15000.0, "price": 1.0, "value": 15000.0, "available_units": 15000.0}]}, "mohit-test": {}}}
{"timestamp": "2024-11-02T08:47:00.001003", "state": {"master_account": {}, "test-dev": {"binance_perpetual_testnet": [{"token": "USDT", "units": 15000.0, "price": 1.0, "value": 15000.0, "available_units": 15000.0}]}, "mohit-test": {}}}
{"timestamp": "2024-11-02T08:48:00.002038", "state": {"master_account": {}, "test-dev": {"binance_perpetual_testnet": [{"token": "USDT", "units": 15000.0, "price": 1.0, "value": 15000.0, "available_units": 15000.0}]}, "mohit-test": {}}}
{"timestamp": "2024-11-02T08:48:00.002541", "state": {"master_account": {}, "test-dev": {"binance_perpetual_testnet": [{"token": "USDT", "units": 15000.0, "price": 1.0, "value": 15000.0, "available_units": 15000.0}]}, "mohit-test": {}}}
{"timestamp": "2024-11-02T08:49:00.000156", "state": {"master_account": {}, "test-dev": {"binance_perpetual_testnet": [{"token": "USDT", "units": 15000.0, "price": 1.0, "value": 15000.0, "available_units": 15000.0}]}, "mohit-test": {}}}
{"timestamp": "2024-11-02T08:49:00.000638", "state": {"master_account": {}, "test-dev": {"binance_perpetual_testnet": [{"token": "USDT", "units": 15000.0, "price": 1.0, "value": 15000.0, "available_units": 15000.0}]}, "mohit-test": {}}}
{"timestamp": "2024-11-02T08:50:00.000206", "state": {"master_account": {}, "test-dev": {"binance_perpetual_testnet": [{"token": "USDT", "units": 15000.0, "price": 1.0, "value": 15000.0, "available_units": 15000.0}]}, "mohit-test": {}}}
{"timestamp": "2024-11-02T08:50:00.000742", "state": {"master_account": {}, "test-dev": {"binance_perpetual_testnet": [{"token": "USDT", "units": 15000.0, "price": 1.0, "value": 15000.0, "available_units": 15000.0}]}, "mohit-test": {}}}
{"timestamp": "2024-11-02T08:51:00.000105", "state": {"master_account": {}, "test-dev": {"binance_perpetual_testnet": [{"token": "USDT", "units": 15000.0, "price": 1.0, "value": 15000.0, "available_units": 15000.0}]}, "mohit-test": {}}}
{"timestamp": "2024-11-02T08:51:00.000607", "state": {"master_account": {}, "test-dev": {"binance_perpetual_testnet": [{"token": "USDT", "units": 15000.0, "price": 1.0, "value": 15000.0, "available_units": 15000.0}]}, "mohit-test": {}}}
{"timestamp": "2024-11-02T08:52:28.293534", "state": {"master_account": {}, "test-dev": {"binance_perpetual_testnet": [{"token": "USDT", "units": 15000.0, "price": 1.0, "value": 15000.0, "available_units": 15000.0}]}, "mohit-test": {}}}
{"timestamp": "2024-11-02T08:52:28.293783", "state": {"master_account": {}, "test-dev": {"binance_perpetual_testnet": [{"token": "USDT", "units": 15000.0, "price": 1.0, "value": 15000.0, "available_units": 15000.0}]}, "mohit-test": {}}}
{"timestamp": "2024-11-02T08:52:59.999457", "state": {"master_account": {}, "test-dev": {"binance_perpetual_testnet": [{"token": "USDT", "units": 15000.0, "price": 1.0, "value": 15000.0, "available_units": 15000.0}]}, "mohit-test": {}}}
{"timestamp": "2024-11-02T08:52:59.999921", "state": {"master_account": {}, "test-dev": {"binance_perpetual_testnet": [{"token": "USDT", "units": 15000.0, "price": 1.0, "value": 15000.0, "available_units": 15000.0}]}, "mohit-test": {}}}
{"timestamp": "2024-11-02T08:53:00.000124", "state": {"master_account": {}, "test-dev": {"binance_perpetual_testnet": [{"token": "USDT", "units": 15000.0, "price": 1.0, "value": 15000.0, "available_units": 15000.0}]}, "mohit-test": {}}}
{"timestamp": "2024-11-02T08:53:59.999800", "state": {"master_account": {}, "test-dev": {"binance_perpetual_testnet": [{"token": "USDT", "units": 15000.0, "price": 1.0, "value": 15000.0, "available_units": 15000.0}]}, "mohit-test": {}}}
{"timestamp": "2024-11-02T08:54:00.000385", "state": {"master_account": {}, "test-dev": {"binance_perpetual_testnet": [{"token": "USDT", "units": 15000.0, "price": 1.0, "value": 15000.0, "available_units": 15000.0}]}, "mohit-test": {}}}
{"timestamp": "2024-11-02T08:55:00.000553", "state": {"master_account": {}, "test-dev": {"binance_perpetual_testnet": [{"token": "USDT", "units": 15000.0, "price": 1.0, "value": 15000.0, "available_units": 15000.0}]}, "mohit-test": {}}}
{"timestamp": "2024-11-02T08:55:00.001029", "state": {"master_account": {}, "test-dev": {"binance_perpetual_testnet": [{"token": "USDT", "units": 15000.0, "price": 1.0, "value": 15000.0, "available_units": 15000.0}]}, "mohit-test": {}}}
{"timestamp": "2024-11-02T08:56:00.000222", "state": {"master_account": {}, "test-dev": {"binance_perpetual_testnet": [{"token": "USDT", "units": 15000.0, "price": 1.0, "value": 15000.0, "available_units": 15000.0}]}, "mohit-test": {}}}
{"timestamp": "2024-11-02T08:56:00.000734", "state": {"master_account": {}, "test-dev": {"binance_perpetual_testnet": [{"token": "USDT", "units": 15000.0, "price": 1.0, "value": 15000.0, "available_units": 15000.0}]}, "mohit-test": {}}}
{"timestamp": "2024-11-02T08:57:00.000552", "state": {"master_account": {}, "test-dev": {"binance_perpetual_testnet": [{"token": "USDT", "units": 15000.0, "price": 1.0, "value": 15000.0, "available_units": 15000.0}]}, "mohit-test": {}}}
{"timestamp": "2024-11-02T08:57:00.001123", "state": {"master_account": {}, "test-dev": {"binance_perpetual_testnet": [{"token": "USDT", "units": 15000.0, "price": 1.0, "value": 15000.0, "available_units": 15000.0}]}, "mohit-test": {}}}
{"timestamp": "2024-11-02T08:58:00.005504", "state": {"master_account": {}, "test-dev": {"binance_perpetual_testnet": [{"token": "USDT", "units": 15000.0, "price": 1.0, "value": 15000.0, "available_units": 15000.0}]}, "mohit-test": {}}}
{"timestamp": "2024-11-02T08:58:00.005924", "state": {"master_account": {}, "test-dev": {"binance_perpetual_testnet": [{"token": "USDT", "units": 15000.0, "price": 1.0, "value": 15000.0, "available_units": 15000.0}]}, "mohit-test": {}}}
{"timestamp": "2024-11-02T08:58:59.999852", "state": {"master_account": {}, "test-dev": {"binance_perpetual_testnet": [{"token": "USDT", "units": 15000.0, "price": 1.0, "value": 15000.0, "available_units": 15000.0}]}, "mohit-test": {}}}
{"timestamp": "2024-11-02T08:59:00.000395", "state": {"master_account": {}, "test-dev": {"binance_perpetual_testnet": [{"token": "USDT", "units": 15000.0, "price": 1.0, "value": 15000.0, "available_units": 15000.0}]}, "mohit-test": {}}}
{"timestamp": "2024-11-02T09:00:00.000220", "state": {"master_account": {}, "test-dev": {"binance_perpetual_testnet": [{"token": "USDT", "units": 15000.0, "price": 1.0, "value": 15000.0, "available_units": 15000.0}]}, "mohit-test": {}}}
{"timestamp": "2024-11-02T09:00:00.000716", "state": {"master_account": {}, "test-dev": {"binance_perpetual_testnet": [{"token": "USDT", "units": 15000.0, "price": 1.0, "value": 15000.0, "available_units": 15000.0}]}, "mohit-test": {}}}
{"timestamp": "2024-11-02T09:01:00.000894", "state": {"master_account": {}, "test-dev": {"binance_perpetual_testnet": [{"token": "USDT", "units": 15000.0, "price": 1.0, "value": 15000.0, "available_units": 15000.0}]}, "mohit-test": {}}}
{"timestamp": "2024-11-02T09:01:00.001536", "state": {"master_account": {}, "test-dev": {"binance_perpetual_testnet": [{"token": "USDT", "units": 15000.0, "price": 1.0, "value": 15000.0, "available_units": 15000.0}]}, "mohit-test": {}}}
{"timestamp": "2024-11-02T09:02:00.000431", "state": {"master_account": {}, "test-dev": {"binance_perpetual_testnet": [{"token": "USDT", "units": 15000.0, "price": 1.0, "value": 15000.0, "available_units": 15000.0}]}, "mohit-test": {}}}
{"timestamp": "2024-11-02T09:02:00.002272", "state": {"master_account": {}, "test-dev": {"binance_perpetual_testnet": [{"token": "USDT", "units": 15000.0, "price": 1.0, "value": 15000.0, "available_units": 15000.0}]}, "mohit-test": {}}}
{"timestamp": "2024-11-02T09:03:00.001520", "state": {"master_account": {}, "test-dev": {"binance_perpetual_testnet": [{"token": "USDT", "units": 15000.0, "price": 1.0, "value": 15000.0, "available_units": 15000.0}]}, "mohit-test": {}}}
{"timestamp": "2024-11-02T09:03:00.003803", "state": {"master_account": {}, "test-dev": {"binance_perpetual_testnet": [{"token": "USDT", "units": 15000.0, "price": 1.0, "value": 15000.0, "available_units": 15000.0}]}, "mohit-test": {}}}
{"timestamp": "2024-11-02T09:04:00.000219", "state": {"master_account": {}, "test-dev": {"binance_perpetual_testnet": [{"token": "USDT", "units": 15000.0, "price": 1.0, "value": 15000.0, "available_units": 15000.0}]}, "mohit-test": {}}}
{"timestamp": "2024-11-02T09:04:00.000806", "state": {"master_account": {}, "test-dev": {"binance_perpetual_testnet": [{"token": "USDT", "units": 15000.0, "price": 1.0, "value": 15000.0, "available_units": 15000.0}]}, "mohit-test": {}}}
{"timestamp": "2024-11-02T09:05:00.000083", "state": {"master_account": {}, "test-dev": {"binance_perpetual_testnet": [{"token": "USDT", "units": 15000.0, "price": 1.0, "value": 15000.0, "available_units": 15000.0}]}, "mohit-test": {}}}
{"timestamp": "2024-11-02T09:05:00.000570", "state": {"master_account": {}, "test-dev": {"binance_perpetual_testnet": [{"token": "USDT", "units": 15000.0, "price": 1.0, "value": 15000.0, "available_units": 15000.0}]}, "mohit-test": {}}}
{"timestamp": "2024-11-02T09:06:00.000268", "state": {"master_account": {}, "test-dev": {"binance_perpetual_testnet": [{"token": "USDT", "units": 15000.0, "price": 1.0, "value": 15000.0, "available_units": 15000.0}]}, "mohit-test": {}}}
{"timestamp": "2024-11-02T09:06:00.001561", "state": {"master_account": {}, "test-dev": {"binance_perpetual_testnet": [{"token": "USDT", "units": 15000.0, "price": 1.0, "value": 15000.0, "available_units": 15000.0}]}, "mohit-test": {}}}
{"timestamp": "2024-11-02T09:07:00.000508", "state": {"master_account": {}, "test-dev": {"binance_perpetual_testnet": [{"token": "USDT", "units": 15000.0, "price": 1.0, "value": 15000.0, "available_units": 15000.0}]}, "mohit-test": {}}}
{"timestamp": "2024-11-02T09:07:00.001038", "state": {"master_account": {}, "test-dev": {"binance_perpetual_testnet": [{"token": "USDT", "units": 15000.0, "price": 1.0, "value": 15000.0, "available_units": 15000.0}]}, "mohit-test": {}}}
{"timestamp": "2024-11-02T09:08:00.000117", "state": {"master_account": {}, "test-dev": {"binance_perpetual_testnet": [{"token": "USDT", "units": 15000.0, "price": 1.0, "value": 15000.0, "available_units": 15000.0}]}, "mohit-test": {}}}
{"timestamp": "2024-11-02T09:08:00.000849", "state": {"master_account": {}, "test-dev": {"binance_perpetual_testnet": [{"token": "USDT", "units": 15000.0, "price": 1.0, "value": 15000.0, "available_units": 15000.0}]}, "mohit-test": {}}}
{"timestamp": "2024-11-02T09:09:00.000659", "state": {"master_account": {}, "test-dev": {"binance_perpetual_testnet": [{"token": "USDT", "units": 15000.0, "price": 1.0, "value": 15000.0, "available_units": 15000.0}]}, "mohit-test": {}}}
{"timestamp": "2024-11-02T09:09:00.001088", "state": {"master_account": {}, "test-dev": {"binance_perpetual_testnet": [{"token": "USDT", "units": 15000.0, "price": 1.0, "value": 15000.0, "available_units": 15000.0}]}, "mohit-test": {}}}
{"timestamp": "2024-11-02T09:10:00.000610", "state": {"master_account": {}, "test-dev": {"binance_perpetual_testnet": [{"token": "USDT", "units": 15000.0, "price": 1.0, "value": 15000.0, "available_units": 15000.0}]}, "mohit-test": {}}}
{"timestamp": "2024-11-02T09:10:00.001848", "state": {"master_account": {}, "test-dev": {"binance_perpetual_testnet": [{"token": "USDT", "units": 15000.0, "price": 1.0, "value": 15000.0, "available_units": 15000.0}]}, "mohit-test": {}}}
{"timestamp": "2024-11-02T09:10:59.999862", "state": {"master_account": {}, "test-dev": {"binance_perpetual_testnet": [{"token": "USDT", "units": 15000.0, "price": 1.0, "value": 15000.0, "available_units": 15000.0}]}, "mohit-test": {}}}
{"timestamp": "2024-11-02T09:11:00.000371", "state": {"master_account": {}, "test-dev": {"binance_perpetual_testnet": [{"token": "USDT", "units": 15000.0, "price": 1.0, "value": 15000.0, "available_units": 15000.0}]}, "mohit-test": {}}}
{"timestamp": "2024-11-02T09:12:00.000205", "state": {"master_account": {}, "test-dev": {"binance_perpetual_testnet": [{"token": "USDT", "units": 15000.0, "price": 1.0, "value": 15000.0, "available_units": 15000.0}]}, "mohit-test": {}}}
{"timestamp": "2024-11-02T09:12:00.001848", "state": {"master_account": {}, "test-dev": {"binance_perpetual_testnet": [{"token": "USDT", "units": 15000.0, "price": 1.0, "value": 15000.0, "available_units": 15000.0}]}, "mohit-test": {}}}
